pichart.py
PiChart-2.2.0.dist-info/LICENSE
PiChart-2.2.0.dist-info/METADATA
PiChart-2.2.0.dist-info/WHEEL
PiChart-2.2.0.dist-info/top_level.txt
PiChart-2.2.0.dist-info/RECORD
