Metadata-Version: 2.2
Name: PiChart
Version: 2.2.0
Summary: Tiny Charts Dashboard UI for MicroPython
License: The MIT License (MIT)
Project-URL: Homepage, http://www.kevsrobots.com
Project-URL: GitHub, https://www.github.com/kevinmcaleer/pichart
Project-URL: YouTube, https://www.youtube.com/c/kevinmcaleer28
License-File: LICENSE
Provides-Extra: dev
Requires-Dist: bumpver; extra == "dev"
Requires-Dist: pip-tools; extra == "dev"
